pydantic_handler_converter/__init__.py
pydantic_handler_converter/abstract_handler.py
pydantic_handler_converter/controller/__init__.py
pydantic_handler_converter/controller/abstract.py
pydantic_handler_converter/controller/base.py
pydantic_handler_converter/controller/bool.py
pydantic_handler_converter/controller/custom_data_str/__init__.py
pydantic_handler_converter/controller/custom_data_str/base.py
pydantic_handler_converter/controller/custom_data_str/main.py
pydantic_handler_converter/controller/custom_data_str/multiple.py
pydantic_handler_converter/controller/custom_data_str/single.py
pydantic_handler_converter/controller/date.py
pydantic_handler_converter/controller/enum/__init__.py
pydantic_handler_converter/controller/enum/base.py
pydantic_handler_converter/controller/enum/main.py
pydantic_handler_converter/controller/enum/multiple.py
pydantic_handler_converter/controller/enum/single.py
pydantic_handler_converter/controller/factory.py
pydantic_handler_converter/controller/float.py
pydantic_handler_converter/controller/int.py
pydantic_handler_converter/controller/string.py
pydantic_handler_converter/dialecsts.py
pydantic_handler_converter/field_factory/__init__.py
pydantic_handler_converter/field_factory/base.py
pydantic_handler_converter/field_factory/enum.py
pydantic_handler_converter/field_factory/main.py
pydantic_handler_converter/field_factory/model.py
pydantic_handler_converter/field_factory/mult_single_splitter.py
pydantic_handler_converter/field_factory/union.py
pydantic_handler_converter/main.py
pydantic_handler_converter/state_builder.py
pydantic_handler_converter/types.py
pydantic_handler_converter/utils/__init__.py
pydantic_handler_converter/utils/step.py
pydantic_handler_converter/view/__init__.py
pydantic_handler_converter/view/abstract.py
pydantic_handler_converter/view/base.py
pydantic_handler_converter/view/bool.py
pydantic_handler_converter/view/enum.py
pydantic_handler_converter/view/factory.py
pydantic_handler_converter/view/float.py
pydantic_handler_converter-0.1.112.dist-info/METADATA
pydantic_handler_converter-0.1.112.dist-info/WHEEL
pydantic_handler_converter-0.1.112.dist-info/RECORD
